wikidata_sparqlwrapper/__init__.py
wikidata_sparqlwrapper/version.py
wikidata_sparqlwrapper-2025.1.dist-info/METADATA
wikidata_sparqlwrapper-2025.1.dist-info/WHEEL
wikidata_sparqlwrapper-2025.1.dist-info/licenses/LICENSE.txt
wikidata_sparqlwrapper-2025.1.dist-info/RECORD
