Metadata-Version: 2.4
Name: wikidata_sparqlwrapper
Version: 2025.1
Summary: Wrapper around the Wikidata SPARQL endpoint that respects the Wikidata usage policy.
Project-URL: Homepage, https://gitlab.inria.fr/jrye/wikidata-sparqlwrapper
Project-URL: Source, https://gitlab.inria.fr/jrye/wikidata-sparqlwrapper.git
Project-URL: Documentation, https://jrye.gitlabpages.inria.fr/wikidata-sparqlwrapper
Project-URL: Issues, https://gitlab.inria.fr/jrye/wikidata-sparqlwrapper/-/issues
Author-email: Jan-Michael Rye <jan-michael.rye@inria.fr>
License: MIT License
License-File: LICENSE.txt
Classifier: License :: OSI Approved :: MIT License
Classifier: Operating System :: OS Independent
Classifier: Programming Language :: Python :: 3
Requires-Python: >=3.7
Requires-Dist: sparqlwrapper
